minimalANN/__init__.py
minimalANN/activations.py
minimalANN/backpropagation.py
minimalANN/layer.py
minimalANN/main.py
minimalANN/network.py
minimalann-1.0.8.dist-info/licenses/LICENSE
minimalann-1.0.8.dist-info/METADATA
minimalann-1.0.8.dist-info/WHEEL
minimalann-1.0.8.dist-info/top_level.txt
minimalann-1.0.8.dist-info/RECORD
