Metadata-Version: 2.4
Name: minimalANN
Version: 1.0.8
Summary: A minimal barebones ANN library using only numpy
Author-email: Amritanshu Barpanda <your_email@example.com>
License-Expression: MIT
Project-URL: Homepage, https://github.com/ABarpanda/minimalANN
Requires-Python: >=3.10
License-File: LICENSE
Requires-Dist: numpy
Dynamic: license-file
